simple_exact_diagonalization_routines/__init__.py
simple_exact_diagonalization_routines/local_matrix_class.py
simple_exact_diagonalization_routines-0.11.dist-info/LICENSE
simple_exact_diagonalization_routines-0.11.dist-info/METADATA
simple_exact_diagonalization_routines-0.11.dist-info/WHEEL
simple_exact_diagonalization_routines-0.11.dist-info/top_level.txt
simple_exact_diagonalization_routines-0.11.dist-info/RECORD
