Metadata-Version: 2.1
Name: simple-exact-diagonalization-routines
Version: 0.11
Summary: A set of functions useful for quick exact diagonalization computations and checks.
Home-page: https://github.com/marekgluza/simple_exact_diagonalization_routines
Author: Marek Gluza
License: GPL-3.0
Platform: UNKNOWN
License-File: LICENSE
Requires-Dist: numpy
